points_fl/__init__.py
points_fl/base.py
points_fl/federated_learning.py
points_fl/flask_api.py
points_fl/inference.py
points_fl/log_provider.py
points_fl/permission.py
points_fl/proto/__init__.py
points_fl/proto/federated_learning_pb2.py
points_fl/proto/federated_learning_pb2_grpc.py
points_fl/proto/inference_pb2.py
points_fl/proto/inference_pb2_grpc.py
points_fl/proto/log_provider_pb2.py
points_fl/proto/log_provider_pb2_grpc.py
points_fl/proto/permission_pb2.py
points_fl/proto/permission_pb2_grpc.py
points_fl-1.0.4.dist-info/LICENSE
points_fl-1.0.4.dist-info/METADATA
points_fl-1.0.4.dist-info/WHEEL
points_fl-1.0.4.dist-info/top_level.txt
points_fl-1.0.4.dist-info/RECORD
