Metadata-Version: 2.1
Name: points-fl
Version: 1.0.4
Summary: Points FL SDK
Home-page: https://github.com/points-org/fl_server_sdk
Author: points
Author-email: info@points.org
License: Apache License
Keywords: points,points_fl,federated_learning
Platform: any
Requires-Python: >=3.6
Requires-Dist: grpcio
Requires-Dist: grpcio-tools
Requires-Dist: protobuf
Requires-Dist: requests
